ivande_combiner/__init__.py
ivande_combiner/etl.py
ivande_combiner/feature_engineering.py
ivande_combiner/transformers.py
ivande_combiner/utils.py
ivande_combiner/ts/__init__.py
ivande_combiner/ts/hg.py
ivande_combiner/ts/metrics.py
ivande_combiner/ts/ts_utils.py
tests/__init__.py
tests/test_feature_engineering.py
tests/test_transformers.py
ivande_combiner-0.0.41.dist-info/LICENSE.txt
ivande_combiner-0.0.41.dist-info/METADATA
ivande_combiner-0.0.41.dist-info/WHEEL
ivande_combiner-0.0.41.dist-info/top_level.txt
ivande_combiner-0.0.41.dist-info/RECORD
