Metadata-Version: 2.1
Name: ivande-combiner
Version: 0.0.41
Summary: basic functionality for classic sklearn ml
Home-page: https://github.com/IvanDe83/ivande_combiner
Author: IvanDe
Author-email: ivande83@gmail.com
License: MIT
Classifier: Development Status :: 3 - Alpha
Classifier: Intended Audience :: Developers
Classifier: License :: OSI Approved :: MIT License
Classifier: Programming Language :: Python :: 3
Classifier: Programming Language :: Python :: 3.13
License-File: LICENSE.txt
Requires-Dist: scikit-learn~=1.6.1
Requires-Dist: pandas~=2.2.3
Requires-Dist: requests~=2.32.3
Requires-Dist: sqlalchemy~=2.0.36
Requires-Dist: psycopg2-binary~=2.9.10
